{
  "id": "ownerDigestCron01",
  "name": "Owner Digest — 5 Minute Cron",
  "active": true,
  "versionId": "9cdb3a7b-43c8-4b06-9d18-0b78b8210ce1",
  "nodes": [
    {
      "parameters": {
        "rule": {
          "interval": [
            {
              "field": "cronExpression",
              "expression": "*/5 * * * *"
            }
          ]
        }
      },
      "id": "schedule-trigger",
      "name": "Every 5 Minutes",
      "type": "n8n-nodes-base.scheduleTrigger",
      "typeVersion": 1.2,
      "position": [
        240,
        300
      ]
    },
    {
      "parameters": {},
      "id": "manual-trigger",
      "name": "Manual Trigger",
      "type": "n8n-nodes-base.manualTrigger",
      "typeVersion": 1,
      "position": [
        240,
        460
      ]
    },
    {
      "parameters": {
        "mode": "runOnceForAllItems",
        "jsCode": "const cron = $env.CRON_SECRET;\nif (!cron) throw new Error('CRON_SECRET missing from n8n environment variables');\n\nconst res = await this.helpers.httpRequest({\n  method: 'POST',\n  url: 'https://franchisetech.ro/api/cron/owner-digest',\n  headers: { Authorization: 'Bearer ' + cron },\n  json: true,\n  returnFullResponse: true,\n});\n\nif (res.statusCode !== 200) {\n  throw new Error('Digest cron failed: HTTP ' + res.statusCode + ' — ' + JSON.stringify(res.body));\n}\n\nconst { checked = 0, due = 0, sent = 0, failed = 0, skipped = 0, recipientsSent = 0, recipientsFailed = 0 } = res.body || {};\nreturn [{ json: { checked, due, sent, failed, skipped, recipientsSent, recipientsFailed, ok: failed === 0 } }];"
      },
      "id": "call-digest",
      "name": "Call Owner Digest Cron",
      "type": "n8n-nodes-base.code",
      "typeVersion": 2,
      "position": [
        480,
        380
      ]
    },
    {
      "parameters": {
        "resource": "message",
        "operation": "sendMessage",
        "chatId": "8505337023",
        "text": "={{ '✉️ Owner digest: ' + $json.sent + ' orgs sent / ' + $json.recipientsSent + ' recipients, ' + $json.failed + ' failed, ' + $json.skipped + ' skipped, ' + $json.due + ' due (checked: ' + $json.checked + ')' }}",
        "additionalFields": {
          "appendAttribution": false
        }
      },
      "id": "telegram-result",
      "name": "Telegram — Digest Result",
      "type": "n8n-nodes-base.telegram",
      "typeVersion": 1.2,
      "position": [
        720,
        380
      ],
      "credentials": {
        "telegramApi": {
          "name": "My Telegram"
        }
      }
    }
  ],
  "connections": {
    "Every 5 Minutes": {
      "main": [
        [
          {
            "node": "Call Owner Digest Cron",
            "type": "main",
            "index": 0
          }
        ]
      ]
    },
    "Manual Trigger": {
      "main": [
        [
          {
            "node": "Call Owner Digest Cron",
            "type": "main",
            "index": 0
          }
        ]
      ]
    },
    "Call Owner Digest Cron": {
      "main": [
        [
          {
            "node": "Telegram — Digest Result",
            "type": "main",
            "index": 0
          }
        ]
      ]
    }
  },
  "settings": {
    "executionOrder": "v1"
  }
}
